{
  "code": 200,
  "status": "OK",
  "data": [
    {
      "timings": {
        "Fajr": "05:14",
        "Dhuhr": "12:24",
        "Asr": "03:45",
        "Maghrib": "06:15",
        "Isha": "07:25"
      },
      "date": {
        "gregorian": {
          "date": "1-03-2021"
        },
        "hijri": {
          "date": "17-07-1442"
        }
      }
    },
    {
      "timings": {
        "Fajr": "05:13",
        "Dhuhr": "12:24",
        "Asr": "03:45",
        "Maghrib": "06:15",
        "Isha": "07:25"
      },
      "date": {
        "gregorian": {
          "date": "2-03-2021"
        },
        "hijri": {
          "date": "18-07-1442"
        }
      }
    },
    {
      "timings": {
        "Fajr": "05:12",
        "Dhuhr": "12:24",
        "Asr": "03:45",
        "Maghrib": "06:16",
        "Isha": "07:26"
      },
      "date": {
        "gregorian": {
          "date": "3-03-2021"
        },
        "hijri": {
          "date": "19-07-1442"
        }
      }
    },
    {
      "timings": {
        "Fajr": "05:11",
        "Dhuhr": "12:24",
        "Asr": "03:45",
        "Maghrib": "06:16",
        "Isha": "07:26"
      },
      "date": {
        "gregorian": {
          "date": "4-03-2021"
        },
        "hijri": {
          "date": "20-07-1442"
        }
      }
    },
    {
      "timings": {
        "Fajr": "05:10",
        "Dhuhr": "12:23",
        "Asr": "03:45",
        "Maghrib": "06:16",
        "Isha": "07:27"
      },
      "date": {
        "gregorian": {
          "date": "5-03-2021"
        },
        "hijri": {
          "date": "21-07-1442"
        }
      }
    },
    {
      "timings": {
        "Fajr": "05:09",
        "Dhuhr": "12:23",
        "Asr": "03:46",
        "Maghrib": "06:17",
        "Isha": "07:27"
      },
      "date": {
        "gregorian": {
          "date": "6-03-2021"
        },
        "hijri": {
          "date": "22-07-1442"
        }
      }
    },
    {
      "timings": {
        "Fajr": "05:09",
        "Dhuhr": "12:23",
        "Asr": "03:46",
        "Maghrib": "06:17",
        "Isha": "07:27"
      },
      "date": {
        "gregorian": {
          "date": "7-03-2021"
        },
        "hijri": {
          "date": "23-07-1442"
        }
      }
    },
    {
      "timings": {
        "Fajr": "05:08",
        "Dhuhr": "12:23",
        "Asr": "03:46",
        "Maghrib": "06:18",
        "Isha": "07:28"
      },
      "date": {
        "gregorian": {
          "date": "8-03-2021"
        },
        "hijri": {
          "date": "24-07-1442"
        }
      }
    },
    {
      "timings": {
        "Fajr": "05:07",
        "Dhuhr": "12:22",
        "Asr": "03:46",
        "Maghrib": "06:18",
        "Isha": "07:28"
      },
      "date": {
        "gregorian": {
          "date": "9-03-2021"
        },
        "hijri": {
          "date": "25-07-1442"
        }
      }
    },
    {
      "timings": {
        "Fajr": "05:06",
        "Dhuhr": "12:22",
        "Asr": "03:46",
        "Maghrib": "06:19",
        "Isha": "07:29"
      },
      "date": {
        "gregorian": {
          "date": "10-03-2021"
        },
        "hijri": {
          "date": "26-07-1442"
        }
      }
    },
    {
      "timings": {
        "Fajr": "05:05",
        "Dhuhr": "12:22",
        "Asr": "03:46",
        "Maghrib": "06:19",
        "Isha": "07:29"
      },
      "date": {
        "gregorian": {
          "date": "11-03-2021"
        },
        "hijri": {
          "date": "27-07-1442"
        }
      }
    },
    {
      "timings": {
        "Fajr": "05:04",
        "Dhuhr": "12:22",
        "Asr": "03:46",
        "Maghrib": "06:20",
        "Isha": "07:30"
      },
      "date": {
        "gregorian": {
          "date": "12-03-2021"
        },
        "hijri": {
          "date": "28-07-1442"
        }
      }
    },
    {
      "timings": {
        "Fajr": "05:03",
        "Dhuhr": "12:21",
        "Asr": "03:46",
        "Maghrib": "06:20",
        "Isha": "07:30"
      },
      "date": {
        "gregorian": {
          "date": "13-03-2021"
        },
        "hijri": {
          "date": "29-07-1442"
        }
      }
    }
  ]
}
